DEV.txt
LICENSE.txt
MANIFEST.in
README.rst
pylint.rc
saemref-client.py
setup.cfg
setup.py
test.py
tox.ini
saemref_client/__init__.py
saemref_client/__main__.py
saemref_client/eac.py
saemref_client/skos.py
saemref_client.egg-info/PKG-INFO
saemref_client.egg-info/SOURCES.txt
saemref_client.egg-info/dependency_links.txt
saemref_client.egg-info/entry_points.txt
saemref_client.egg-info/requires.txt
saemref_client.egg-info/top_level.txt