Metadata-Version: 1.0
Name: saemref-client
Version: 0.1.2
Summary: Command-line client for a SAEM site
Home-page: https://framagit.org/saemproject/saem-client
Author: Logilab SA
Author-email: contact@logilab.fr
License: LGPL
Keywords: client saem oaipmh eac skos
Platform: UNKNOWN
